vnnlib/__init__.py
vnnlib/__init__.pyi
vnnlib/_core.cpp
vnnlib/_core.cpython-310-x86_64-linux-gnu.so
vnnlib/_core.pyi
vnnlib/libVNNLib.so
vnnlib/py.typed
vnnlib/compat/__init__.py
vnnlib/compat/py.typed
vnnlib.libs/libgcc_s-0cd532bd.so.1
vnnlib.libs/libstdc++-5d72f927.so.6.0.33
vnnlib-1.0.0.dist-info/METADATA
vnnlib-1.0.0.dist-info/WHEEL
vnnlib-1.0.0.dist-info/RECORD
vnnlib-1.0.0.dist-info/licenses/LICENSE
vnnlib-1.0.0.dist-info/sboms/auditwheel.cdx.json
