Metadata-Version: 2.2
Name: vnnlib
Version: 1.0.0
Summary: Python bindings for VNNLib parsing and AST manipulation
Author-Email: Allen Antony <allenantony2001@gmail.com>
License: MIT
Requires-Python: >=3.7
Requires-Dist: pybind11>=2.6.0
